pdl/__init__.py
pdl/pdl.py
pdl/version.py
pdl-0.9.0.dist-info/LICENSE
pdl-0.9.0.dist-info/METADATA
pdl-0.9.0.dist-info/WHEEL
pdl-0.9.0.dist-info/top_level.txt
pdl-0.9.0.dist-info/RECORD
